murphet/__init__.py
murphet/churn_model.py
murphet/murphet_beta.stan
murphet/murphet_gauss.stan
murphet/seasonality.py
murphet-1.6.6.dist-info/licenses/LICENSE
murphet-1.6.6.dist-info/METADATA
murphet-1.6.6.dist-info/WHEEL
murphet-1.6.6.dist-info/top_level.txt
murphet-1.6.6.dist-info/RECORD
