Metadata-Version: 2.4
Name: murphet
Version: 1.6.6
Summary: Bayesian time‑series model with Beta/Gaussian heads, smooth changepoints and seasonality
Author: Stephen Murphy
Author-email: Stephen Murphy <stephenjmurph@gmail.com>
License: MIT
Project-URL: Homepage, https://murphet.com
Project-URL: Repository, https://github.com/halsted312/murphet
Project-URL: Issue Tracker, https://github.com/halsted312/murphet/issues
Project-URL: Documentation, https://murphet.com/docs
Keywords: prophet,time series,bayesian forecasting,beta regression,churn modelling,seasonality,changepoint detection,stan,churn rates,probability forecasting,stock price changes,murphet,forecasting,prediction
Classifier: Development Status :: 4 - Beta
Classifier: Intended Audience :: Developers
Classifier: Intended Audience :: Science/Research
Classifier: Topic :: Scientific/Engineering :: Information Analysis
Classifier: Topic :: Software Development :: Libraries :: Python Modules
Classifier: License :: OSI Approved :: MIT License
Classifier: Programming Language :: Python :: 3
Classifier: Programming Language :: Python :: 3 :: Only
Classifier: Programming Language :: Python :: 3.9
Classifier: Programming Language :: Python :: 3.10
Classifier: Framework :: Matplotlib
Classifier: Framework :: Jupyter
Classifier: Topic :: Scientific/Engineering :: Mathematics
Classifier: Topic :: Utilities
Requires-Python: >=3.8
License-File: LICENSE
Requires-Dist: cmdstanpy>=1.1.0
Requires-Dist: numpy>=1.22
Requires-Dist: pandas>=1.5
Requires-Dist: scipy>=1.9
Provides-Extra: dev
Requires-Dist: pytest>=7; extra == "dev"
Requires-Dist: build; extra == "dev"
Requires-Dist: black; extra == "dev"
Requires-Dist: pre-commit; extra == "dev"
Provides-Extra: plot
Requires-Dist: matplotlib>=3.7; extra == "plot"
Requires-Dist: seaborn>=0.13; extra == "plot"
Provides-Extra: extra
Requires-Dist: optuna>=3; extra == "extra"
Requires-Dist: prophet>=1.1; extra == "extra"
Dynamic: author
Dynamic: license-file
Dynamic: requires-python
